vt_ugcs/__init__.py
vt_ugcs/__main__.py
vt_ugcs/serve.py
vt_ugcs/assets/favicon.ico
vt_ugcs/assets/vt512.png
vt_ugcs/assets/bootstrap-5.3.3-dist/css/bootstrap-grid.css
vt_ugcs/assets/bootstrap-5.3.3-dist/css/bootstrap-grid.css.map
vt_ugcs/assets/bootstrap-5.3.3-dist/css/bootstrap-grid.min.css
vt_ugcs/assets/bootstrap-5.3.3-dist/css/bootstrap-grid.min.css.map
vt_ugcs/assets/bootstrap-5.3.3-dist/css/bootstrap-grid.rtl.css
vt_ugcs/assets/bootstrap-5.3.3-dist/css/bootstrap-grid.rtl.css.map
vt_ugcs/assets/bootstrap-5.3.3-dist/css/bootstrap-grid.rtl.min.css
vt_ugcs/assets/bootstrap-5.3.3-dist/css/bootstrap-grid.rtl.min.css.map
vt_ugcs/assets/bootstrap-5.3.3-dist/css/bootstrap-reboot.css
vt_ugcs/assets/bootstrap-5.3.3-dist/css/bootstrap-reboot.css.map
vt_ugcs/assets/bootstrap-5.3.3-dist/css/bootstrap-reboot.min.css
vt_ugcs/assets/bootstrap-5.3.3-dist/css/bootstrap-reboot.min.css.map
vt_ugcs/assets/bootstrap-5.3.3-dist/css/bootstrap-reboot.rtl.css
vt_ugcs/assets/bootstrap-5.3.3-dist/css/bootstrap-reboot.rtl.css.map
vt_ugcs/assets/bootstrap-5.3.3-dist/css/bootstrap-reboot.rtl.min.css
vt_ugcs/assets/bootstrap-5.3.3-dist/css/bootstrap-reboot.rtl.min.css.map
vt_ugcs/assets/bootstrap-5.3.3-dist/css/bootstrap-utilities.css
vt_ugcs/assets/bootstrap-5.3.3-dist/css/bootstrap-utilities.css.map
vt_ugcs/assets/bootstrap-5.3.3-dist/css/bootstrap-utilities.min.css
vt_ugcs/assets/bootstrap-5.3.3-dist/css/bootstrap-utilities.min.css.map
vt_ugcs/assets/bootstrap-5.3.3-dist/css/bootstrap-utilities.rtl.css
vt_ugcs/assets/bootstrap-5.3.3-dist/css/bootstrap-utilities.rtl.css.map
vt_ugcs/assets/bootstrap-5.3.3-dist/css/bootstrap-utilities.rtl.min.css
vt_ugcs/assets/bootstrap-5.3.3-dist/css/bootstrap-utilities.rtl.min.css.map
vt_ugcs/assets/bootstrap-5.3.3-dist/css/bootstrap.css
vt_ugcs/assets/bootstrap-5.3.3-dist/css/bootstrap.css.map
vt_ugcs/assets/bootstrap-5.3.3-dist/css/bootstrap.min.css
vt_ugcs/assets/bootstrap-5.3.3-dist/css/bootstrap.min.css.map
vt_ugcs-1.0.0.dist-info/LICENSE
vt_ugcs-1.0.0.dist-info/METADATA
vt_ugcs-1.0.0.dist-info/WHEEL
vt_ugcs-1.0.0.dist-info/entry_points.txt
vt_ugcs-1.0.0.dist-info/top_level.txt
vt_ugcs-1.0.0.dist-info/RECORD
